pyboy/__init__.cpython-311-aarch64-linux-musl.so
pyboy/__init__.py
pyboy/__main__.py
pyboy/conftest.py
pyboy/default_rom.gb
pyboy/pyboy.cpython-311-aarch64-linux-musl.so
pyboy/pyboy.pxd
pyboy/pyboy.py
pyboy/utils.cpython-311-aarch64-linux-musl.so
pyboy/utils.pxd
pyboy/utils.py
pyboy/api/__init__.cpython-311-aarch64-linux-musl.so
pyboy/api/__init__.py
pyboy/api/constants.cpython-311-aarch64-linux-musl.so
pyboy/api/constants.py
pyboy/api/gameshark.cpython-311-aarch64-linux-musl.so
pyboy/api/gameshark.pxd
pyboy/api/gameshark.py
pyboy/api/memory_scanner.cpython-311-aarch64-linux-musl.so
pyboy/api/memory_scanner.pxd
pyboy/api/memory_scanner.py
pyboy/api/screen.cpython-311-aarch64-linux-musl.so
pyboy/api/screen.pxd
pyboy/api/screen.py
pyboy/api/sound.cpython-311-aarch64-linux-musl.so
pyboy/api/sound.pxd
pyboy/api/sound.py
pyboy/api/sprite.cpython-311-aarch64-linux-musl.so
pyboy/api/sprite.pxd
pyboy/api/sprite.py
pyboy/api/tile.cpython-311-aarch64-linux-musl.so
pyboy/api/tile.pxd
pyboy/api/tile.py
pyboy/api/tilemap.cpython-311-aarch64-linux-musl.so
pyboy/api/tilemap.pxd
pyboy/api/tilemap.py
pyboy/core/__init__.cpython-311-aarch64-linux-musl.so
pyboy/core/__init__.py
pyboy/core/bootrom.cpython-311-aarch64-linux-musl.so
pyboy/core/bootrom.pxd
pyboy/core/bootrom.py
pyboy/core/bootrom_cgb.bin
pyboy/core/bootrom_dmg.bin
pyboy/core/cpu.cpython-311-aarch64-linux-musl.so
pyboy/core/cpu.pxd
pyboy/core/cpu.py
pyboy/core/interaction.cpython-311-aarch64-linux-musl.so
pyboy/core/interaction.pxd
pyboy/core/interaction.py
pyboy/core/lcd.cpython-311-aarch64-linux-musl.so
pyboy/core/lcd.pxd
pyboy/core/lcd.py
pyboy/core/mb.cpython-311-aarch64-linux-musl.so
pyboy/core/mb.pxd
pyboy/core/mb.py
pyboy/core/opcodes.cpython-311-aarch64-linux-musl.so
pyboy/core/opcodes.pxd
pyboy/core/opcodes.py
pyboy/core/opcodes_gen.py
pyboy/core/ram.cpython-311-aarch64-linux-musl.so
pyboy/core/ram.pxd
pyboy/core/ram.py
pyboy-2.7.0.dist-info/METADATA
pyboy-2.7.0.dist-info/WHEEL
pyboy-2.7.0.dist-info/entry_points.txt
pyboy-2.7.0.dist-info/top_level.txt
pyboy-2.7.0.dist-info/RECORD
pyboy-2.7.0.dist-info/licenses/LICENSE.md
