Metadata-Version: 2.4
Name: pyboy
Version: 2.7.0
Summary: Game Boy emulator written in Python
Author-email: Mads Ynddal <mads@ynddal.dk>
License-Expression: LGPL-3.0-only
Project-URL: Homepage, https://github.com/Baekalfen/PyBoy
Project-URL: Documentation, https://docs.pyboy.dk/index.html
Project-URL: Repository, https://github.com/Baekalfen/PyBoy.git
Keywords: gameboy,game boy,emulator,cython,pypy
Classifier: Operating System :: OS Independent
Classifier: Programming Language :: Cython
Classifier: Programming Language :: Python :: 3
Classifier: Programming Language :: Python :: Implementation :: PyPy
Classifier: Topic :: System :: Emulators
Requires-Python: >=3.9
License-File: LICENSE.md
Requires-Dist: numpy
Requires-Dist: pysdl2
Requires-Dist: pysdl2-dll
Provides-Extra: all
Requires-Dist: pyopengl; extra == "all"
Requires-Dist: glfw; extra == "all"
Requires-Dist: PyOpenAL; extra == "all"
Requires-Dist: markdown; extra == "all"
Requires-Dist: pdoc3; extra == "all"
Requires-Dist: gym; extra == "all"
Dynamic: license-file
